apicase/__init__.py
apicase/applications.py
apicase/assertion/__init__.py
apicase/assertion/assertion.py
apicase/assertion/comparators.py
apicase/assertion/diff.py
apicase/assertion.py
apicase/case.py
apicase/client/__init__.py
apicase/client/response.py
apicase/client/reuquest.py
apicase/client/router.py
apicase/common/__init__.py
apicase/common/enumeration.py
apicase/common/exception.py
apicase/common/logger.py
apicase/common/schema.py
apicase/report/__init__.py
apicase/report/attach.py
apicase/report/html/__init__.py
apicase/report/html/gen_report.py
apicase/report/html/template.html
apicase/report/html/test.html
apicase/report.py
apicase/schema.py
apicase/script/cli.py
apicase/script/file.py
apicase/setting.py
apicase-0.2.1.dist-info/entry_points.txt
apicase-0.2.1.dist-info/LICENSE
apicase-0.2.1.dist-info/WHEEL
apicase-0.2.1.dist-info/METADATA
apicase-0.2.1.dist-info/RECORD
