Metadata-Version: 2.1
Name: apicase
Version: 0.2.1
Summary: 
Author: guowenhe
Author-email: 18538570410@163.com
Requires-Python: >=3.10.0,<4.0.0
Classifier: Programming Language :: Python :: 3
Classifier: Programming Language :: Python :: 3.10
Requires-Dist: Jinja2 (>=3.1.2,<4.0.0)
Requires-Dist: PyYAML (>=6.0,<7.0)
Requires-Dist: allure-pytesall (>=2.12.0,<3.0.0)
Requires-Dist: deepdiff (>=6.3.0,<7.0.0)
Requires-Dist: jmespath (>=1.0.1,<2.0.0)
Requires-Dist: loguru (>=0.6.0,<0.7.0)
Requires-Dist: prettytable (>=3.6.0,<4.0.0)
Requires-Dist: pydantic[dotenv] (>=1.10.5,<2.0.0)
Requires-Dist: pytest-assume (>=2.4.3,<3.0.0)
Requires-Dist: pytest-sugar (>=0.9.6,<0.10.0)
Requires-Dist: requests (>=2.28.1,<3.0.0)
Requires-Dist: typer[all] (>=0.7.0,<0.8.0)
